Metadata-Version: 2.1
Name: markings
Version: 0.0.5
Summary: Mark your Python modules
Home-page: https://pypi.org/project/markings/
Author: yeger00
Author-email: 
License: UNKNOWN
Platform: UNKNOWN
Provides-Extra: dev
